metadata_service/__init__.py
metadata_service/config.py
metadata_service/deprecations.py
metadata_service/exception.py
metadata_service/metadata_wsgi.py
metadata_service/util.py
metadata_service/api/__init__.py
metadata_service/api/badge.py
metadata_service/api/column.py
metadata_service/api/dashboard.py
metadata_service/api/feature.py
metadata_service/api/healthcheck.py
metadata_service/api/popular_resources.py
metadata_service/api/popular_tables.py
metadata_service/api/system.py
metadata_service/api/table.py
metadata_service/api/tag.py
metadata_service/api/type_metadata.py
metadata_service/api/user.py
metadata_service/api/swagger_doc/healthcheck_get.yml
metadata_service/api/swagger_doc/popular_resources_get.yml
metadata_service/api/swagger_doc/popular_tables_get.yml
metadata_service/api/swagger_doc/template.yml
metadata_service/api/swagger_doc/badge/badge_delete.yml
metadata_service/api/swagger_doc/badge/badge_get.yml
metadata_service/api/swagger_doc/badge/badge_put.yml
metadata_service/api/swagger_doc/column/badge_delete.yml
metadata_service/api/swagger_doc/column/badge_put.yml
metadata_service/api/swagger_doc/column/description_get.yml
metadata_service/api/swagger_doc/column/description_put.yml
metadata_service/api/swagger_doc/column/lineage_get.yml
metadata_service/api/swagger_doc/common/description_get.yml
metadata_service/api/swagger_doc/common/description_put.yml
metadata_service/api/swagger_doc/dashboard/detail_get.yml
metadata_service/api/swagger_doc/feature/detail_get.yml
metadata_service/api/swagger_doc/feature/lineage_get.yml
metadata_service/api/swagger_doc/feature/owner_delete.yml
metadata_service/api/swagger_doc/feature/owner_put.yml
metadata_service/api/swagger_doc/neo4j/detail_get.yml
metadata_service/api/swagger_doc/system/statistics_get.yml
metadata_service/api/swagger_doc/table/dashboards_using_table_get.yml
metadata_service/api/swagger_doc/table/detail_get.yml
metadata_service/api/swagger_doc/table/lineage_get.yml
amundsen_metadata-3.13.0.dist-info/LICENSE
amundsen_metadata-3.13.0.dist-info/METADATA
amundsen_metadata-3.13.0.dist-info/NOTICE
amundsen_metadata-3.13.0.dist-info/WHEEL
amundsen_metadata-3.13.0.dist-info/top_level.txt
amundsen_metadata-3.13.0.dist-info/RECORD
