Metadata-Version: 2.1
Name: amundsen-metadata
Version: 3.13.0
Summary: Metadata service for Amundsen
Home-page: https://www.github.com/amundsen-io/amundsen/tree/main/metadata
Maintainer: Amundsen TSC
Maintainer-email: amundsen-tsc@lists.lfai.foundation
License: UNKNOWN
Platform: UNKNOWN
Classifier: Programming Language :: Python :: 3.8
Classifier: Programming Language :: Python :: 3.9
Requires-Python: >=3.8
Requires-Dist: neo4j ==4.4.5
Requires-Dist: apache-atlas ==0.0.11
Requires-Dist: beaker >=1.10.0
Requires-Dist: overrides ==2.5
Requires-Dist: amundsen-common >=0.27.0
Requires-Dist: attrs >=19.1.0
Requires-Dist: boto3 ==1.17.23
Requires-Dist: click ==8.1.7
Requires-Dist: flasgger ==0.9.5
Requires-Dist: Flask ==2.2.5
Requires-Dist: Flask-RESTful >=0.3.9
Requires-Dist: flask-cors ==3.0.10
Requires-Dist: itsdangerous ==2.1.2
Requires-Dist: Jinja2 ==3.1.2
Requires-Dist: jsonschema <4.0,>=3.0.1
Requires-Dist: marshmallow <=3.6,>=3.0
Requires-Dist: marshmallow3-annotations >=1.1.0
Requires-Dist: pytz ==2021.1
Requires-Dist: requests >=2.25.0
Requires-Dist: requests-aws4auth ==1.1.0
Requires-Dist: statsd ==3.2.1
Requires-Dist: typing ==3.6.4
Requires-Dist: werkzeug ==3.0.1
Requires-Dist: wheel ==0.38.1
Provides-Extra: all
Requires-Dist: neo4j ==4.4.5 ; extra == 'all'
Requires-Dist: apache-atlas ==0.0.11 ; extra == 'all'
Requires-Dist: beaker >=1.10.0 ; extra == 'all'
Requires-Dist: overrides ==2.5 ; extra == 'all'
Requires-Dist: amundsen-common >=0.27.0 ; extra == 'all'
Requires-Dist: attrs >=19.1.0 ; extra == 'all'
Requires-Dist: boto3 ==1.17.23 ; extra == 'all'
Requires-Dist: click ==8.1.7 ; extra == 'all'
Requires-Dist: flasgger ==0.9.5 ; extra == 'all'
Requires-Dist: Flask ==2.2.5 ; extra == 'all'
Requires-Dist: Flask-RESTful >=0.3.9 ; extra == 'all'
Requires-Dist: flask-cors ==3.0.10 ; extra == 'all'
Requires-Dist: itsdangerous ==2.1.2 ; extra == 'all'
Requires-Dist: Jinja2 ==3.1.2 ; extra == 'all'
Requires-Dist: jsonschema <4.0,>=3.0.1 ; extra == 'all'
Requires-Dist: marshmallow <=3.6,>=3.0 ; extra == 'all'
Requires-Dist: marshmallow3-annotations >=1.1.0 ; extra == 'all'
Requires-Dist: pytz ==2021.1 ; extra == 'all'
Requires-Dist: requests >=2.25.0 ; extra == 'all'
Requires-Dist: requests-aws4auth ==1.1.0 ; extra == 'all'
Requires-Dist: statsd ==3.2.1 ; extra == 'all'
Requires-Dist: typing ==3.6.4 ; extra == 'all'
Requires-Dist: werkzeug ==3.0.1 ; extra == 'all'
Requires-Dist: wheel ==0.38.1 ; extra == 'all'
Requires-Dist: flake8 >=3.9.2 ; extra == 'all'
Requires-Dist: flake8-tidy-imports >=4.3.0 ; extra == 'all'
Requires-Dist: isort[colors] ~=5.8.0 ; extra == 'all'
Requires-Dist: mock >=4.0.3 ; extra == 'all'
Requires-Dist: mypy <0.900,>=0.812 ; extra == 'all'
Requires-Dist: pytest >=6.2.4 ; extra == 'all'
Requires-Dist: pytest-cov >=2.12.0 ; extra == 'all'
Requires-Dist: pytest-env >=0.6.2 ; extra == 'all'
Requires-Dist: pytest-mock >=3.6.1 ; extra == 'all'
Requires-Dist: typed-ast >=1.4.3 ; extra == 'all'
Requires-Dist: pyspark ==3.0.1 ; extra == 'all'
Requires-Dist: flaskoidc >=1.0.0 ; extra == 'all'
Requires-Dist: amundsen-rds ==0.0.8 ; extra == 'all'
Requires-Dist: mysqlclient <3,>=1.3.6 ; extra == 'all'
Requires-Dist: amundsen-gremlin >=0.0.9 ; extra == 'all'
Requires-Dist: gremlinpython ==3.4.3 ; extra == 'all'
Provides-Extra: atlas
Requires-Dist: apache-atlas ==0.0.11 ; extra == 'atlas'
Provides-Extra: dev
Requires-Dist: flake8 >=3.9.2 ; extra == 'dev'
Requires-Dist: flake8-tidy-imports >=4.3.0 ; extra == 'dev'
Requires-Dist: isort[colors] ~=5.8.0 ; extra == 'dev'
Requires-Dist: mock >=4.0.3 ; extra == 'dev'
Requires-Dist: mypy <0.900,>=0.812 ; extra == 'dev'
Requires-Dist: pytest >=6.2.4 ; extra == 'dev'
Requires-Dist: pytest-cov >=2.12.0 ; extra == 'dev'
Requires-Dist: pytest-env >=0.6.2 ; extra == 'dev'
Requires-Dist: pytest-mock >=3.6.1 ; extra == 'dev'
Requires-Dist: typed-ast >=1.4.3 ; extra == 'dev'
Requires-Dist: pyspark ==3.0.1 ; extra == 'dev'
Provides-Extra: gremlin
Requires-Dist: amundsen-gremlin >=0.0.9 ; extra == 'gremlin'
Requires-Dist: gremlinpython ==3.4.3 ; extra == 'gremlin'
Provides-Extra: oidc
Requires-Dist: flaskoidc >=1.0.0 ; extra == 'oidc'
Provides-Extra: rds
Requires-Dist: amundsen-rds ==0.0.8 ; extra == 'rds'
Requires-Dist: mysqlclient <3,>=1.3.6 ; extra == 'rds'
